open_terminalui/__about__.py
open_terminalui/__init__.py
open_terminalui/_models.py
open_terminalui/_themes.py
open_terminalui/app.py
open_terminalui/chat_manager.py
open_terminalui/document_manager.py
open_terminalui/entry_points.py
open_terminalui/memory_manager.py
open_terminalui/styles.tcss
open_terminalui/components/__init__.py
open_terminalui/components/chat_list_item.py
open_terminalui/components/chat_message.py
open_terminalui/screens/document_screen.py
open_terminalui/tools/__init__.py
open_terminalui/tools/document_search.py
open_terminalui/tools/memory_search.py
open_terminalui/tools/web_search.py
open_terminalui-0.0.3.dist-info/METADATA
open_terminalui-0.0.3.dist-info/WHEEL
open_terminalui-0.0.3.dist-info/entry_points.txt
open_terminalui-0.0.3.dist-info/licenses/LICENSE.txt
open_terminalui-0.0.3.dist-info/RECORD
