Metadata-Version: 2.4
Name: open-terminalui
Version: 0.0.3
Summary: Terminal UI application for interacting with local LLMs via ollama.
Project-URL: Documentation, https://github.com/Andrew Hall/open-terminalui#readme
Project-URL: Issues, https://github.com/Andrew Hall/open-terminalui/issues
Project-URL: Source, https://github.com/Andrew Hall/open-terminalui
Author-email: Andrew Hall <andrewmartinhall2@gmail.com>
License-Expression: MIT
License-File: LICENSE.txt
Classifier: Development Status :: 4 - Beta
Classifier: Programming Language :: Python
Classifier: Programming Language :: Python :: 3.11
Classifier: Programming Language :: Python :: 3.12
Classifier: Programming Language :: Python :: 3.13
Classifier: Programming Language :: Python :: Implementation :: CPython
Classifier: Programming Language :: Python :: Implementation :: PyPy
Requires-Python: >=3.11
Requires-Dist: chromadb>=1.3.5
Requires-Dist: ddgs>=9.9.3
Requires-Dist: ollama>=0.6.1
Requires-Dist: pypdf>=6.4.0
Requires-Dist: textual[syntax]>=0.73.0
